src/verilog/F74F283.sv

module F74F283(
    input logic  [3:0] a,
    input logic  [3:0] b,
    input logic        ci,
    output logic [3:0] s,
    output logic       co
);
    logic [4:0] sum;
    logic [3:0] a_dlyd, b_dlyd;

    /* Delays are added to inputs and output to match datasheet values as 
       close as possible. When Tphl and Tplh differ, the worst is taken.
       This is done because a transition at one input may cause an output
       to go high or low. A more detailed model would be needed to capture
       that behavior correctly. */
    buf #(2:4:6) I0( ci_dlyd, ci);
    buf #(2:4:6) I1[3:0]( a_dlyd, a);
    buf #(2:4:6) I2[3:0]( b_dlyd, b);

    assign sum = {1'b0,a_dlyd} + {1'b0,b_dlyd} + ci_dlyd;

    buf #(4:3:4.5) I3[3:0]( s, sum[3:0]);
    buf #(1.5:1.7:2.5) I4( co, sum[4]);
endmodule



module ttl_74F377(
    input  logic       clk,
    input  logic       nEN,
    input  logic [7:0] D,
    output logic [7:0] Q
);
logic Qi;

always_ff @(posedge clk) begin
    if (clk && nEN == 1'b0)
        Qi <= D;
end

assign #(3.0:6.0:7.5,4.0:7.0:9.0) Q = Qi;

    specify
        // $setuphold(reference, data, setup_time, hold_time)
        $setuphold(posedge clk, D, 3.5, 1.0); 
        $setuphold(posedge clk, nEN, 4.1, 2.0); 
    endspecify
endmodule



module ttl_74F244(
    output logic [3:0] Y,
    input  logic [3:0] D,
    input  logic       nOE
);
    logic       nOE1i, nOE2i;
    logic [3:0] Di, nDi;
    wire  [3:0] y;

    buf #( 1.0:1.0:1.2, 1.0:1.0:1.5) I1a(  Di[0], D[0]);
    buf #( 1.0:1.0:1.2, 1.0:1.0:1.5) I1b(  Di[1], D[1]);
    buf #( 1.0:1.0:1.2, 1.0:1.0:1.5) I1c(  Di[2], D[2]);
    buf #( 1.0:1.0:1.2, 1.0:1.0:1.5) I1d(  Di[3], D[3]);

    not #( 1.0:1.0:1.5, 1.0:1.0:1.2) I2a( nDi[0], D[0]);
    not #( 1.0:1.0:1.5, 1.0:1.0:1.2) I2b( nDi[1], D[1]);
    not #( 1.0:1.0:1.5, 1.0:1.0:1.2) I2c( nDi[2], D[2]);
    not #( 1.0:1.0:1.5, 1.0:1.0:1.2) I2d( nDi[3], D[3]);

    buf #( 0.5:1.5:2.0, 0.5:1.3:1.7) I3( nOEh, nOE);
    buf #( 0.5:1.5:2.0, 0.5:2.4:3.0) I4( nOEl, nOE);

    bufif0 #( 1.5:3.0:5.0, 1.5:3.0:5.0, 1.5:3.0:5.0) I4ha( y[0], 4'b1111, nOEh |  nDi[0]);
    bufif0 #( 1.5:3.0:5.0, 1.5:3.0:5.0, 1.5:3.0:5.0) I4la( y[0], 4'b0000, nOEl |   Di[0]);
    bufif0 #( 1.5:3.0:5.0, 1.5:3.0:5.0, 1.5:3.0:5.0) I4hb( y[1], 4'b1111, nOEh |  nDi[1]);
    bufif0 #( 1.5:3.0:5.0, 1.5:3.0:5.0, 1.5:3.0:5.0) I4lb( y[1], 4'b0000, nOEl |   Di[1]);
    bufif0 #( 1.5:3.0:5.0, 1.5:3.0:5.0, 1.5:3.0:5.0) I4hc( y[2], 4'b1111, nOEh |  nDi[2]);
    bufif0 #( 1.5:3.0:5.0, 1.5:3.0:5.0, 1.5:3.0:5.0) I4lc( y[2], 4'b0000, nOEl |   Di[2]);
    bufif0 #( 1.5:3.0:5.0, 1.5:3.0:5.0, 1.5:3.0:5.0) I4hd( y[3], 4'b1111, nOEh |  nDi[3]);
    bufif0 #( 1.5:3.0:5.0, 1.5:3.0:5.0, 1.5:3.0:5.0) I4ld( y[3], 4'b0000, nOEl |   Di[3]);
    assign Y = y;
endmodule

/*********
  To do:
    Priority:
      74F244, 74F245, 74F374/574, 74F182, 74F381, 74F382, 74F157
      74F138, 4-bit sync counter with load and reset, 74F74, 74F174/6
      SRAM: 8kx8, 32kx8, 64kx8
    Maybe:
      74F181
*********/

src/verilog/F74F283_5inputEncoder_tb.sv

`timescale 1ns / 1ns
`include "F74F283.sv"

module tb;
    logic [3:0] a, b, s;
    logic co;

    logic [4:0] in;
    logic [2:0] out;

    logic init;

    F74F283 dut( a, b, s[3] & init, s, co);
    assign a = {in[3:2], 1'b0, in[0]};
    assign b = {in[4], in[2], co & init, in[1]};
    assign out = s[2:0];

    initial begin
        $display("\n", `__FILE__, " - Starting simulation.");
        $dumpfile("./vcd/F74F283_5inputEncoder_tb.vcd");
        $dumpvars(0, tb);

        in = 0;
        init = 0;
        #20 init=1;
        for ( integer i = 0; i < 32; i = i + 1) begin
            in = i;
            #20;
        end

        #20;
        $display( `__FILE__, " - Test complete!\n");
        $finish;
    end

    initial begin
        $monitor("Time=%0t, in=%d, out=%d", $time, in, out);
    end

endmodule



// Makes to carry-save-adders-3-2 out of a 74F283
module two_csa32(
    input  logic [2:0] a1,
    input  logic [2:0] a2,
    output logic [1:0] y1,
    output logic [1:0] y2
);
    logic [3:0] a, b;
    logic [3:0] s;
    logic ci, co;

    assign a = {a2[0], a2[2], 1'b0, a1[0]};
    assign b = {a2[1], a2[2], 1'b0, a1[1]};

    F74F283 U1( a, b, a1[2], s, co);

    assign y1 = s[1:0];
    assign y2 = {co,s[3]};
endmodule



module csa53(
    input  logic [4:0] i,
    output logic [2:0] cnt
);
    logic cin, co;
    logic init;

    F74F283 U1(
        .a( {i[3:2], 1'b0, i[0]}),
        .b( {i[4], i[2], co & init, i[1]}),
        .ci( ci & init),
        .s({ci, cnt[2:0]}),
        .co( co)
    );

    initial begin
        init = 0;
        #10 init = 1;
    end
endmodule



module popcnt16 (
    input  [15:0] i,
    output  [4:0] cnt
);
    logic [2:0] a0, a1;
    logic [1:0] a2, a3;
    logic [3:0] s0, s1;
    logic nc1, nc2;

    csa53 U1( i[4:0], a0[2:0]);
    csa53 U2( i[12:8], a1[2:0]);
    two_csa32 U3( i[7:5], i[15:13], a2[1:0], a3[1:0]);
    F74F283 U4( {1'b0, a0}, {2'b0,a2}, 1'b0, s0, nc1);
    F74F283 U5( {1'b0, a1}, {2'b0,a3}, 1'b0, s1, nc2);
    F74F283 U6( s0, s1, 1'b0, cnt[3:0], cnt[4]);
endmodule



module majorityGate (
    input  [4:0] i,
    output       m
);
    logic nc0, nc1, s3, co;

    F74F283 U1(
        .a( { i[3], i[2], co, i[0]}),
        .b( { i[4], i[2], s3, i[1]}),
        .ci( co),
        .s( { s3, m, nc1, nc0}),
        .co( co)
    );
endmodule

src/verilog/vcd/F74F283_5inputEncoder_tb.vcd
$date
	Sat Feb 21 23:30:08 2026
$end
$version
	Icarus Verilog
$end
$timescale
	1ns
$end
$scope module tb $end
$var wire 4 ! s [3:0] $end
$var wire 3 " out [2:0] $end
$var wire 1 # co $end
$var wire 4 $ b [3:0] $end
$var wire 4 % a [3:0] $end
$var reg 5 & in [4:0] $end
$var reg 1 ' init $end
$scope module dut $end
$var wire 4 ( a [3:0] $end
$var wire 4 ) a_dlyd [3:0] $end
$var wire 4 * b [3:0] $end
$var wire 4 + b_dlyd [3:0] $end
$var wire 1 , ci $end
$var wire 1 - ci_dlyd $end
$var wire 1 # co $end
$var wire 4 . s [3:0] $end
$var wire 5 / sum [4:0] $end
$upscope $end
$scope begin $ivl_for_loop0 $end
$var integer 32 0 i [31:0] $end
$upscope $end
$upscope $end
$enddefinitions $end
$comment Show the parameter values. $end
$dumpall
$end
#0
$dumpvars
bx 0
bx /
bx .
x-
0,
bx +
b0 *
bx )
b0 (
0'
b0 &
b0 %
b0 $
x#
bx "
bx !
$end
#4
b0 /
b0 +
0-
b0 )
#6
0#
#7
b0 "
b0 !
b0 .
#20
b0 0
1'
#40
b1 %
b1 (
b1 &
b1 0
#44
b1 /
b1 )
#47
b1 "
b1 !
b1 .
#60
b0 %
b0 (
b1 $
b1 *
b10 &
b10 0
#64
b0 )
b1 /
b1 +
#80
b1 %
b1 (
b11 &
b11 0
#84
b10 /
b1 )
#87
b10 "
b10 !
b10 .
#100
b100 %
b100 (
b100 $
b100 *
b100 &
b100 0
#104
b100 )
b1000 /
b100 +
#107
1,
b0 "
b1000 !
b1000 .
#111
b1001 /
1-
#114
b1 "
b1001 !
b1001 .
#120
b101 %
b101 (
b101 &
b101 0
#124
b1010 /
b101 )
#127
b10 "
b1010 !
b1010 .
#140
b100 %
b100 (
b101 $
b101 *
b110 &
b110 0
#144
b100 )
b1010 /
b101 +
#160
b101 %
b101 (
b111 &
b111 0
#164
b1011 /
b101 )
#167
b11 "
b1011 !
b1011 .
#180
b1000 %
b1000 (
b0 $
b0 *
b1000 &
b1000 0
#184
b1000 )
b1001 /
b0 +
#187
b1 "
b1001 !
b1001 .
#200
b1001 %
b1001 (
b1001 &
b1001 0
#204
b1010 /
b1001 )
#207
b10 "
b1010 !
b1010 .
#220
b1000 %
b1000 (
b1 $
b1 *
b1010 &
b1010 0
#224
b1000 )
b1010 /
b1 +
#240
b1001 %
b1001 (
b1011 &
b1011 0
#244
b1011 /
b1001 )
#247
b11 "
b1011 !
b1011 .
#260
b1100 %
b1100 (
b100 $
b100 *
b1100 &
b1100 0
#264
b1100 )
b10001 /
b100 +
#266
b110 $
b110 *
1#
#267
0,
b1 "
b1 !
b1 .
#270
b10011 /
b110 +
#271
b10010 /
0-
#274
b10 "
b10 !
b10 .
#280
b1101 %
b1101 (
b1101 &
b1101 0
#284
b10011 /
b1101 )
#287
b11 "
b11 !
b11 .
#300
b1100 %
b1100 (
b111 $
b111 *
b1110 &
b1110 0
#304
b1100 )
b10011 /
b111 +
#320
b1101 %
b1101 (
b1111 &
b1111 0
#324
b10100 /
b1101 )
#327
b100 "
b100 !
b100 .
#340
b0 %
b0 (
b1010 $
b1010 *
b10000 &
b10000 0
#344
b0 )
b1010 /
b1010 +
#346
b1000 $
b1000 *
0#
#347
1,
b10 "
b1010 !
b1010 .
#350
b1000 /
b1000 +
#351
b1001 /
1-
#354
b1 "
b1001 !
b1001 .
#360
b1 %
b1 (
b10001 &
b10001 0
#364
b1010 /
b1 )
#367
b10 "
b1010 !
b1010 .
#380
b0 %
b0 (
b1001 $
b1001 *
b10010 &
b10010 0
#384
b0 )
b1010 /
b1001 +
#400
b1 %
b1 (
b10011 &
b10011 0
#404
b1011 /
b1 )
#407
b11 "
b1011 !
b1011 .
#420
b100 %
b100 (
b1100 $
b1100 *
b10100 &
b10100 0
#424
b100 )
b10001 /
b1100 +
#426
b1110 $
b1110 *
1#
#427
0,
b1 "
b1 !
b1 .
#430
b10011 /
b1110 +
#431
b10010 /
0-
#434
b10 "
b10 !
b10 .
#440
b101 %
b101 (
b10101 &
b10101 0
#444
b10011 /
b101 )
#447
b11 "
b11 !
b11 .
#460
b100 %
b100 (
b1111 $
b1111 *
b10110 &
b10110 0
#464
b100 )
b10011 /
b1111 +
#480
b101 %
b101 (
b10111 &
b10111 0
#484
b10100 /
b101 )
#487
b100 "
b100 !
b100 .
#500
b1000 %
b1000 (
b1010 $
b1010 *
b11000 &
b11000 0
#504
b1000 )
b10010 /
b1010 +
#507
b10 "
b10 !
b10 .
#520
b1001 %
b1001 (
b11001 &
b11001 0
#524
b10011 /
b1001 )
#527
b11 "
b11 !
b11 .
#540
b1000 %
b1000 (
b1011 $
b1011 *
b11010 &
b11010 0
#544
b1000 )
b10011 /
b1011 +
#560
b1001 %
b1001 (
b11011 &
b11011 0
#564
b10100 /
b1001 )
#567
b100 "
b100 !
b100 .
#580
b1100 %
b1100 (
b1110 $
b1110 *
b11100 &
b11100 0
#584
b1100 )
b11010 /
b1110 +
#587
1,
b10 "
b1010 !
b1010 .
#591
b11011 /
1-
#594
b11 "
b1011 !
b1011 .
#600
b1101 %
b1101 (
b11101 &
b11101 0
#604
b11100 /
b1101 )
#607
b100 "
b1100 !
b1100 .
#620
b1100 %
b1100 (
b1111 $
b1111 *
b11110 &
b11110 0
#624
b1100 )
b11100 /
b1111 +
#640
b1101 %
b1101 (
b11111 &
b11111 0
#644
b11101 /
b1101 )
#647
b101 "
b1101 !
b1101 .
#660
b100000 0
