src/verilog/F74F283.sv

module F74F283(
    input logic  [3:0] a,
    input logic  [3:0] b,
    input logic        ci,
    output logic [3:0] s,
    output logic       co
);
    logic [4:0] sum;
    logic [3:0] a_dlyd, b_dlyd;

    /* Delays are added to inputs and output to match datasheet values as 
       close as possible. When Tphl and Tplh differ, the worst is taken.
       This is done because a transition at one input may cause an output
       to go high or low. A more detailed model would be needed to capture
       that behavior correctly. */
    buf #(2:4:6) I0( ci_dlyd, ci);
    buf #(2:4:6) I1[3:0]( a_dlyd, a);
    buf #(2:4:6) I2[3:0]( b_dlyd, b);

    assign sum = {1'b0,a_dlyd} + {1'b0,b_dlyd} + ci_dlyd;

    buf #(4:3:4.5) I3[3:0]( s, sum[3:0]);
    buf #(1.5:1.7:2.5) I4( co, sum[4]);
endmodule



module ttl_74F377(
    input  logic       clk,
    input  logic       nEN,
    input  logic [7:0] D,
    output logic [7:0] Q
);
logic Qi;

always_ff @(posedge clk) begin
    if (clk && nEN == 1'b0)
        Qi <= D;
end

assign #(3.0:6.0:7.5,4.0:7.0:9.0) Q = Qi;

    specify
        // $setuphold(reference, data, setup_time, hold_time)
        $setuphold(posedge clk, D, 3.5, 1.0); 
        $setuphold(posedge clk, nEN, 4.1, 2.0); 
    endspecify
endmodule



module ttl_74F244(
    output logic [3:0] Y,
    input  logic [3:0] D,
    input  logic       nOE
);
    logic       nOE1i, nOE2i;
    logic [3:0] Di, nDi;
    wire  [3:0] y;

    buf #( 1.0:1.0:1.2, 1.0:1.0:1.5) I1a(  Di[0], D[0]);
    buf #( 1.0:1.0:1.2, 1.0:1.0:1.5) I1b(  Di[1], D[1]);
    buf #( 1.0:1.0:1.2, 1.0:1.0:1.5) I1c(  Di[2], D[2]);
    buf #( 1.0:1.0:1.2, 1.0:1.0:1.5) I1d(  Di[3], D[3]);

    not #( 1.0:1.0:1.5, 1.0:1.0:1.2) I2a( nDi[0], D[0]);
    not #( 1.0:1.0:1.5, 1.0:1.0:1.2) I2b( nDi[1], D[1]);
    not #( 1.0:1.0:1.5, 1.0:1.0:1.2) I2c( nDi[2], D[2]);
    not #( 1.0:1.0:1.5, 1.0:1.0:1.2) I2d( nDi[3], D[3]);

    buf #( 0.5:1.5:2.0, 0.5:1.3:1.7) I3( nOEh, nOE);
    buf #( 0.5:1.5:2.0, 0.5:2.4:3.0) I4( nOEl, nOE);

    bufif0 #( 1.5:3.0:5.0, 1.5:3.0:5.0, 1.5:3.0:5.0) I4ha( y[0], 4'b1111, nOEh |  nDi[0]);
    bufif0 #( 1.5:3.0:5.0, 1.5:3.0:5.0, 1.5:3.0:5.0) I4la( y[0], 4'b0000, nOEl |   Di[0]);
    bufif0 #( 1.5:3.0:5.0, 1.5:3.0:5.0, 1.5:3.0:5.0) I4hb( y[1], 4'b1111, nOEh |  nDi[1]);
    bufif0 #( 1.5:3.0:5.0, 1.5:3.0:5.0, 1.5:3.0:5.0) I4lb( y[1], 4'b0000, nOEl |   Di[1]);
    bufif0 #( 1.5:3.0:5.0, 1.5:3.0:5.0, 1.5:3.0:5.0) I4hc( y[2], 4'b1111, nOEh |  nDi[2]);
    bufif0 #( 1.5:3.0:5.0, 1.5:3.0:5.0, 1.5:3.0:5.0) I4lc( y[2], 4'b0000, nOEl |   Di[2]);
    bufif0 #( 1.5:3.0:5.0, 1.5:3.0:5.0, 1.5:3.0:5.0) I4hd( y[3], 4'b1111, nOEh |  nDi[3]);
    bufif0 #( 1.5:3.0:5.0, 1.5:3.0:5.0, 1.5:3.0:5.0) I4ld( y[3], 4'b0000, nOEl |   Di[3]);
    assign Y = y;
endmodule

/*********
  To do:
    Priority:
      74F244, 74F245, 74F374/574, 74F182, 74F381, 74F382, 74F157
      74F138, 4-bit sync counter with load and reset, 74F74, 74F174/6
      SRAM: 8kx8, 32kx8, 64kx8
    Maybe:
      74F181
*********/

src/verilog/F74F283_majority_tb.sv

`timescale 1ns / 100ps
`include "F74F283.sv"

// Output is zero is most bits are zero. Output is one if most inputs are one.
module majorityGate (
    input  [4:0] i,
    output       m
);
    logic nc0, nc1, s3, co, init;

    F74F283 U1(
        .a( { i[3], i[2], co & init, i[0]}),
        .b( { i[4], i[2], s3 & init, i[1]}),
        .ci( co & init),
        .s( { s3, m, nc1, nc0}),
        .co( co)
    );

    initial begin
        init = 0;
        #10 init = 1;
    end
endmodule





module tb;
    logic [4:0] in;
    logic       m;

    majorityGate dut( in, m);

    initial begin
        $display("\n", `__FILE__, " - Starting simulation.");
        $dumpfile("./vcd/F74F283_majority_tb.vcd");
        $dumpvars(0, tb);

        in = 0;
        for ( integer i = 0; i < 32; i = i + 1) begin
            in = 0;
            #40
            in = i;
            #40;
        end

        #40;
        $display( `__FILE__, " - Test complete!\n");
        $finish;
    end

    initial begin
        $monitor("Time=%0t, in=%d, m=%d", $time, in, m);
    end

endmodule

src/verilog/vcd/F74F283_majority_tb.vcd
$date
	Sat Feb 21 22:06:33 2026
$end
$version
	Icarus Verilog
$end
$timescale
	100ps
$end
$scope module tb $end
$var wire 1 ! m $end
$var reg 5 " in [4:0] $end
$scope module dut $end
$var wire 5 # i [4:0] $end
$var wire 1 $ s3 $end
$var wire 1 % nc1 $end
$var wire 1 & nc0 $end
$var wire 1 ! m $end
$var wire 1 ' co $end
$var reg 1 ( init $end
$scope module U1 $end
$var wire 4 ) a [3:0] $end
$var wire 4 * a_dlyd [3:0] $end
$var wire 4 + b [3:0] $end
$var wire 4 , b_dlyd [3:0] $end
$var wire 1 - ci $end
$var wire 1 . ci_dlyd $end
$var wire 1 ' co $end
$var wire 4 / s [3:0] $end
$var wire 5 0 sum [4:0] $end
$upscope $end
$upscope $end
$scope begin $ivl_for_loop0 $end
$var integer 32 1 i [31:0] $end
$upscope $end
$upscope $end
$enddefinitions $end
$comment Show the parameter values. $end
$dumpall
$end
#0
$dumpvars
b0 1
bx 0
bx /
x.
0-
bx ,
b0 +
bx *
b0 )
0(
x'
x&
x%
x$
b0 #
b0 "
x!
$end
#40
b0 0
0.
b0 ,
b0 *
#57
0'
#70
0&
0%
0!
0$
b0 /
#100
1(
#800
b1 1
#1200
b1 )
b1 "
b1 #
#1240
b1 0
b1 *
#1270
1&
b1 /
#1600
b0 )
b0 "
b0 #
b10 1
#1640
b0 0
b0 *
#1670
0&
b0 /
#2000
b1 +
b10 "
b10 #
#2040
b1 0
b1 ,
#2070
1&
b1 /
#2400
b0 +
b0 "
b0 #
b11 1
#2440
b0 0
b0 ,
#2470
0&
b0 /
#2800
b1 )
b1 +
b11 "
b11 #
#2840
b1 *
b10 0
b1 ,
#2870
1%
b10 /
#3200
b0 )
b0 +
b0 "
b0 #
b100 1
#3240
b0 *
b0 0
b0 ,
#3270
0%
b0 /
#3600
b100 )
b100 +
b100 "
b100 #
#3640
b100 *
b1000 0
b100 ,
#3670
b110 +
1$
b1000 /
#3710
b1010 0
b110 ,
#3740
1%
b1010 /
#4000
b0 )
b10 +
b0 "
b0 #
b101 1
#4040
b0 *
b10 0
b10 ,
#4070
b0 +
0$
b10 /
#4110
b0 0
b0 ,
#4140
0%
b0 /
#4400
b101 )
b100 +
b101 "
b101 #
#4440
b101 *
b1001 0
b100 ,
#4470
b110 +
1&
1$
b1001 /
#4510
b1011 0
b110 ,
#4540
1%
b1011 /
#4800
b0 )
b10 +
b0 "
b0 #
b110 1
#4840
b0 *
b10 0
b10 ,
#4870
b0 +
0&
0$
b10 /
#4910
b0 0
b0 ,
#4940
0%
b0 /
#5200
b100 )
b101 +
b110 "
b110 #
#5240
b100 *
b1001 0
b101 ,
#5270
b111 +
1&
1$
b1001 /
#5310
b1011 0
b111 ,
#5340
1%
b1011 /
#5600
b0 )
b10 +
b0 "
b0 #
b111 1
#5640
b0 *
b10 0
b10 ,
#5670
b0 +
0&
0$
b10 /
#5710
b0 0
b0 ,
#5740
0%
b0 /
#6000
b101 )
b101 +
b111 "
b111 #
#6040
b101 *
b1010 0
b101 ,
#6070
b111 +
1%
1$
b1010 /
#6110
b1100 0
b111 ,
#6140
0%
1!
b1100 /
#6400
b0 )
b10 +
b0 "
b0 #
b1000 1
#6440
b0 *
b10 0
b10 ,
#6470
b0 +
1%
0!
0$
b10 /
#6510
b0 0
b0 ,
#6540
0%
b0 /
#6800
b1000 )
b1000 "
b1000 #
#6840
b1000 0
b1000 *
#6870
b10 +
1$
b1000 /
#6910
b1010 0
b10 ,
#6940
1%
b1010 /
#7200
b0 )
b0 "
b0 #
b1001 1
#7240
b10 0
b0 *
#7270
b0 +
0$
b10 /
#7310
b0 0
b0 ,
#7340
0%
b0 /
#7600
b1001 )
b1001 "
b1001 #
#7640
b1001 0
b1001 *
#7670
b10 +
1&
1$
b1001 /
#7710
b1011 0
b10 ,
#7740
1%
b1011 /
#8000
b0 )
b0 "
b0 #
b1010 1
#8040
b10 0
b0 *
#8070
b0 +
0&
0$
b10 /
#8110
b0 0
b0 ,
#8140
0%
b0 /
#8400
b1000 )
b1 +
b1010 "
b1010 #
#8440
b1000 *
b1001 0
b1 ,
#8470
b11 +
1&
1$
b1001 /
#8510
b1011 0
b11 ,
#8540
1%
b1011 /
#8800
b0 )
b10 +
b0 "
b0 #
b1011 1
#8840
b0 *
b10 0
b10 ,
#8870
b0 +
0&
0$
b10 /
#8910
b0 0
b0 ,
#8940
0%
b0 /
#9200
b1001 )
b1 +
b1011 "
b1011 #
#9240
b1001 *
b1010 0
b1 ,
#9270
b11 +
1%
1$
b1010 /
#9310
b1100 0
b11 ,
#9340
0%
1!
b1100 /
#9600
b0 )
b10 +
b0 "
b0 #
b1100 1
#9640
b0 *
b10 0
b10 ,
#9670
b0 +
1%
0!
0$
b10 /
#9710
b0 0
b0 ,
#9740
0%
b0 /
#10000
b1100 )
b100 +
b1100 "
b1100 #
#10040
b1100 *
b10000 0
b100 ,
#10057
1-
b1110 )
1'
#10097
1.
b10011 0
b1110 *
#10127
1&
1%
b11 /
#10400
b10 )
b0 +
b0 "
b0 #
b1101 1
#10440
b10 *
b11 0
b0 ,
#10457
0-
b0 )
0'
#10497
0.
b0 0
b0 *
#10527
0&
0%
b0 /
#10800
b1101 )
b100 +
b1101 "
b1101 #
#10840
b1101 *
b10001 0
b100 ,
#10857
1-
b1111 )
1'
#10870
1&
b1 /
#10897
1.
b10100 0
b1111 *
#10927
0&
1!
b100 /
#11200
b10 )
b0 +
b0 "
b0 #
b1110 1
#11240
b10 *
b11 0
b0 ,
#11257
0-
b0 )
0'
#11270
1&
1%
0!
b11 /
#11297
0.
b0 0
b0 *
#11327
0&
0%
b0 /
#11600
b1100 )
b101 +
b1110 "
b1110 #
#11640
b1100 *
b10001 0
b101 ,
#11657
1-
b1110 )
1'
#11670
1&
b1 /
#11697
1.
b10100 0
b1110 *
#11727
0&
1!
b100 /
#12000
b10 )
b0 +
b0 "
b0 #
b1111 1
#12040
b10 *
b11 0
b0 ,
#12057
0-
b0 )
0'
#12070
1&
1%
0!
b11 /
#12097
0.
b0 0
b0 *
#12127
0&
0%
b0 /
#12400
b1101 )
b101 +
b1111 "
b1111 #
#12440
b1101 *
b10010 0
b101 ,
#12457
1-
b1111 )
1'
#12470
1%
b10 /
#12497
1.
b10101 0
b1111 *
#12527
1&
0%
1!
b101 /
#12800
b10 )
b0 +
b0 "
b0 #
b10000 1
#12840
b10 *
b11 0
b0 ,
#12857
0-
b0 )
0'
#12870
1%
0!
b11 /
#12897
0.
b0 0
b0 *
#12927
0&
0%
b0 /
#13200
b1000 +
b10000 "
b10000 #
#13240
b1000 0
b1000 ,
#13270
b1010 +
1$
b1000 /
#13310
b1010 0
b1010 ,
#13340
1%
b1010 /
#13600
b10 +
b0 "
b0 #
b10001 1
#13640
b10 0
b10 ,
#13670
b0 +
0$
b10 /
#13710
b0 0
b0 ,
#13740
0%
b0 /
#14000
b1 )
b1000 +
b10001 "
b10001 #
#14040
b1 *
b1001 0
b1000 ,
#14070
b1010 +
1&
1$
b1001 /
#14110
b1011 0
b1010 ,
#14140
1%
b1011 /
#14400
b0 )
b10 +
b0 "
b0 #
b10010 1
#14440
b0 *
b10 0
b10 ,
#14470
b0 +
0&
0$
b10 /
#14510
b0 0
b0 ,
#14540
0%
b0 /
#14800
b1001 +
b10010 "
b10010 #
#14840
b1001 0
b1001 ,
#14870
b1011 +
1&
1$
b1001 /
#14910
b1011 0
b1011 ,
#14940
1%
b1011 /
#15200
b10 +
b0 "
b0 #
b10011 1
#15240
b10 0
b10 ,
#15270
b0 +
0&
0$
b10 /
#15310
b0 0
b0 ,
#15340
0%
b0 /
#15600
b1 )
b1001 +
b10011 "
b10011 #
#15640
b1 *
b1010 0
b1001 ,
#15670
b1011 +
1%
1$
b1010 /
#15710
b1100 0
b1011 ,
#15740
0%
1!
b1100 /
#16000
b0 )
b10 +
b0 "
b0 #
b10100 1
#16040
b0 *
b10 0
b10 ,
#16070
b0 +
1%
0!
0$
b10 /
#16110
b0 0
b0 ,
#16140
0%
b0 /
#16400
b100 )
b1100 +
b10100 "
b10100 #
#16440
b100 *
b10000 0
b1100 ,
#16457
1-
b110 )
1'
#16497
1.
b10011 0
b110 *
#16527
1&
1%
b11 /
#16800
b10 )
b0 +
b0 "
b0 #
b10101 1
#16840
b10 *
b11 0
b0 ,
#16857
0-
b0 )
0'
#16897
0.
b0 0
b0 *
#16927
0&
0%
b0 /
#17200
b101 )
b1100 +
b10101 "
b10101 #
#17240
b101 *
b10001 0
b1100 ,
#17257
1-
b111 )
1'
#17270
1&
b1 /
#17297
1.
b10100 0
b111 *
#17327
0&
1!
b100 /
#17600
b10 )
b0 +
b0 "
b0 #
b10110 1
#17640
b10 *
b11 0
b0 ,
#17657
0-
b0 )
0'
#17670
1&
1%
0!
b11 /
#17697
0.
b0 0
b0 *
#17727
0&
0%
b0 /
#18000
b100 )
b1101 +
b10110 "
b10110 #
#18040
b100 *
b10001 0
b1101 ,
#18057
1-
b110 )
1'
#18070
1&
b1 /
#18097
1.
b10100 0
b110 *
#18127
0&
1!
b100 /
#18400
b10 )
b0 +
b0 "
b0 #
b10111 1
#18440
b10 *
b11 0
b0 ,
#18457
0-
b0 )
0'
#18470
1&
1%
0!
b11 /
#18497
0.
b0 0
b0 *
#18527
0&
0%
b0 /
#18800
b101 )
b1101 +
b10111 "
b10111 #
#18840
b101 *
b10010 0
b1101 ,
#18857
1-
b111 )
1'
#18870
1%
b10 /
#18897
1.
b10101 0
b111 *
#18927
1&
0%
1!
b101 /
#19200
b10 )
b0 +
b0 "
b0 #
b11000 1
#19240
b10 *
b11 0
b0 ,
#19257
0-
b0 )
0'
#19270
1%
0!
b11 /
#19297
0.
b0 0
b0 *
#19327
0&
0%
b0 /
#19600
b1000 )
b1000 +
b11000 "
b11000 #
#19640
b1000 *
b10000 0
b1000 ,
#19657
1-
b1010 )
1'
#19697
1.
b10011 0
b1010 *
#19727
1&
1%
b11 /
#20000
b10 )
b0 +
b0 "
b0 #
b11001 1
#20040
b10 *
b11 0
b0 ,
#20057
0-
b0 )
0'
#20097
0.
b0 0
b0 *
#20127
0&
0%
b0 /
#20400
b1001 )
b1000 +
b11001 "
b11001 #
#20440
b1001 *
b10001 0
b1000 ,
#20457
1-
b1011 )
1'
#20470
1&
b1 /
#20497
1.
b10100 0
b1011 *
#20527
0&
1!
b100 /
#20800
b10 )
b0 +
b0 "
b0 #
b11010 1
#20840
b10 *
b11 0
b0 ,
#20857
0-
b0 )
0'
#20870
1&
1%
0!
b11 /
#20897
0.
b0 0
b0 *
#20927
0&
0%
b0 /
#21200
b1000 )
b1001 +
b11010 "
b11010 #
#21240
b1000 *
b10001 0
b1001 ,
#21257
1-
b1010 )
1'
#21270
1&
b1 /
#21297
1.
b10100 0
b1010 *
#21327
0&
1!
b100 /
#21600
b10 )
b0 +
b0 "
b0 #
b11011 1
#21640
b10 *
b11 0
b0 ,
#21657
0-
b0 )
0'
#21670
1&
1%
0!
b11 /
#21697
0.
b0 0
b0 *
#21727
0&
0%
b0 /
#22000
b1001 )
b1001 +
b11011 "
b11011 #
#22040
b1001 *
b10010 0
b1001 ,
#22057
1-
b1011 )
1'
#22070
1%
b10 /
#22097
1.
b10101 0
b1011 *
#22127
1&
0%
1!
b101 /
#22400
b10 )
b0 +
b0 "
b0 #
b11100 1
#22440
b10 *
b11 0
b0 ,
#22457
0-
b0 )
0'
#22470
1%
0!
b11 /
#22497
0.
b0 0
b0 *
#22527
0&
0%
b0 /
#22800
b1100 )
b1100 +
b11100 "
b11100 #
#22840
b1100 *
b11000 0
b1100 ,
#22857
1-
b1110 )
1'
#22870
b1110 +
1$
b1000 /
#22897
1.
b11011 0
b1110 *
#22910
b11101 0
b1110 ,
#22940
1&
1!
b1101 /
#23200
b10 )
b10 +
b0 "
b0 #
b11101 1
#23240
b10 *
b101 0
b10 ,
#23257
0-
b0 )
0'
#23270
b0 +
0$
b101 /
#23297
0.
b10 0
b0 *
#23310
b0 0
b0 ,
#23340
0&
0!
b0 /
#23600
b1101 )
b1100 +
b11101 "
b11101 #
#23640
b1101 *
b11001 0
b1100 ,
#23657
1-
b1111 )
1'
#23670
b1110 +
1&
1$
b1001 /
#23697
1.
b11100 0
b1111 *
#23710
b11110 0
b1110 ,
#23740
0&
1%
1!
b1110 /
#24000
b10 )
b10 +
b0 "
b0 #
b11110 1
#24040
b10 *
b101 0
b10 ,
#24057
0-
b0 )
0'
#24070
b0 +
1&
0%
0$
b101 /
#24097
0.
b10 0
b0 *
#24110
b0 0
b0 ,
#24140
0&
0!
b0 /
#24400
b1100 )
b1101 +
b11110 "
b11110 #
#24440
b1100 *
b11001 0
b1101 ,
#24457
1-
b1110 )
1'
#24470
b1111 +
1&
1$
b1001 /
#24497
1.
b11100 0
b1110 *
#24510
b11110 0
b1111 ,
#24540
0&
1%
1!
b1110 /
#24800
b10 )
b10 +
b0 "
b0 #
b11111 1
#24840
b10 *
b101 0
b10 ,
#24857
0-
b0 )
0'
#24870
b0 +
1&
0%
0$
b101 /
#24897
0.
b10 0
b0 *
#24910
b0 0
b0 ,
#24940
0&
0!
b0 /
#25200
b1101 )
b1101 +
b11111 "
b11111 #
#25240
b1101 *
b11010 0
b1101 ,
#25257
1-
b1111 )
1'
#25270
b1111 +
1%
1$
b1010 /
#25297
1.
b11101 0
b1111 *
#25310
b11111 0
b1111 ,
#25340
1&
1!
b1111 /
#25600
b100000 1
