src/verilog/F74F283.sv

module F74F283(
    input logic  [3:0] a,
    input logic  [3:0] b,
    input logic        ci,
    output logic [3:0] s,
    output logic       co
);
    logic [4:0] sum;
    logic [3:0] a_dlyd, b_dlyd;

    /* Delays are added to inputs and output to match datasheet values as 
       close as possible. When Tphl and Tplh differ, the worst is taken.
       This is done because a transition at one input may cause an output
       to go high or low. A more detailed model would be needed to capture
       that behavior correctly. */
    buf #(2:4:6) I0( ci_dlyd, ci);
    buf #(2:4:6) I1[3:0]( a_dlyd, a);
    buf #(2:4:6) I2[3:0]( b_dlyd, b);

    assign sum = {1'b0,a_dlyd} + {1'b0,b_dlyd} + ci_dlyd;

    buf #(4:3:4.5) I3[3:0]( s, sum[3:0]);
    buf #(1.5:1.7:2.5) I4( co, sum[4]);
endmodule



module ttl_74F377(
    input  logic       clk,
    input  logic       nEN,
    input  logic [7:0] D,
    output logic [7:0] Q
);
logic Qi;

always_ff @(posedge clk) begin
    if (clk && nEN == 1'b0)
        Qi <= D;
end

assign #(3.0:6.0:7.5,4.0:7.0:9.0) Q = Qi;

    specify
        // $setuphold(reference, data, setup_time, hold_time)
        $setuphold(posedge clk, D, 3.5, 1.0); 
        $setuphold(posedge clk, nEN, 4.1, 2.0); 
    endspecify
endmodule



module ttl_74F244(
    output logic [3:0] Y,
    input  logic [3:0] D,
    input  logic       nOE
);
    logic       nOE1i, nOE2i;
    logic [3:0] Di, nDi;
    wire  [3:0] y;

    buf #( 1.0:1.0:1.2, 1.0:1.0:1.5) I1a(  Di[0], D[0]);
    buf #( 1.0:1.0:1.2, 1.0:1.0:1.5) I1b(  Di[1], D[1]);
    buf #( 1.0:1.0:1.2, 1.0:1.0:1.5) I1c(  Di[2], D[2]);
    buf #( 1.0:1.0:1.2, 1.0:1.0:1.5) I1d(  Di[3], D[3]);

    not #( 1.0:1.0:1.5, 1.0:1.0:1.2) I2a( nDi[0], D[0]);
    not #( 1.0:1.0:1.5, 1.0:1.0:1.2) I2b( nDi[1], D[1]);
    not #( 1.0:1.0:1.5, 1.0:1.0:1.2) I2c( nDi[2], D[2]);
    not #( 1.0:1.0:1.5, 1.0:1.0:1.2) I2d( nDi[3], D[3]);

    buf #( 0.5:1.5:2.0, 0.5:1.3:1.7) I3( nOEh, nOE);
    buf #( 0.5:1.5:2.0, 0.5:2.4:3.0) I4( nOEl, nOE);

    bufif0 #( 1.5:3.0:5.0, 1.5:3.0:5.0, 1.5:3.0:5.0) I4ha( y[0], 4'b1111, nOEh |  nDi[0]);
    bufif0 #( 1.5:3.0:5.0, 1.5:3.0:5.0, 1.5:3.0:5.0) I4la( y[0], 4'b0000, nOEl |   Di[0]);
    bufif0 #( 1.5:3.0:5.0, 1.5:3.0:5.0, 1.5:3.0:5.0) I4hb( y[1], 4'b1111, nOEh |  nDi[1]);
    bufif0 #( 1.5:3.0:5.0, 1.5:3.0:5.0, 1.5:3.0:5.0) I4lb( y[1], 4'b0000, nOEl |   Di[1]);
    bufif0 #( 1.5:3.0:5.0, 1.5:3.0:5.0, 1.5:3.0:5.0) I4hc( y[2], 4'b1111, nOEh |  nDi[2]);
    bufif0 #( 1.5:3.0:5.0, 1.5:3.0:5.0, 1.5:3.0:5.0) I4lc( y[2], 4'b0000, nOEl |   Di[2]);
    bufif0 #( 1.5:3.0:5.0, 1.5:3.0:5.0, 1.5:3.0:5.0) I4hd( y[3], 4'b1111, nOEh |  nDi[3]);
    bufif0 #( 1.5:3.0:5.0, 1.5:3.0:5.0, 1.5:3.0:5.0) I4ld( y[3], 4'b0000, nOEl |   Di[3]);
    assign Y = y;
endmodule

/*********
  To do:
    Priority:
      74F244, 74F245, 74F374/574, 74F182, 74F381, 74F382, 74F157
      74F138, 4-bit sync counter with load and reset, 74F74, 74F174/6
      SRAM: 8kx8, 32kx8, 64kx8
    Maybe:
      74F181
*********/

src/verilog/F74F283_tb.sv

`timescale 1ns / 100ps
`include "F74F283.sv"

module tb;
    logic [3:0] a, b, s;
    logic ci, co;

    F74F283 dut( a, b, ci, s, co);

    initial begin
        $display("\n", `__FILE__, " - Starting simulation.");
        $dumpfile("./vcd/F74F283_tb.vcd");
        $dumpvars(0, tb);

        a  = 0;
        b  = 0;
        ci = 0;
        for ( integer i = 0; i < 16; i = i + 1) begin
            for ( integer j = 0; j < 16; j = j + 1) begin
                a = i;
                b = j;
                ci = 0;
                #20;
                ci = 1;
                #20;
            end
        end

        #20;
        $display( `__FILE__, " - Test complete!\n");
        $finish;
    end

    initial begin
        //$monitor("Time=%0t, a=%d, b=%d, ci=%b, s=%d, co=%b", $time, a, b, ci, s, co);
    end

endmodule

src/verilog/vcd/F74F283_tb.vcd
$date
	Sat Feb 21 23:56:27 2026
$end
$version
	Icarus Verilog
$end
$timescale
	100ps
$end
$scope module tb $end
$var wire 4 ! s [3:0] $end
$var wire 1 " co $end
$var reg 4 # a [3:0] $end
$var reg 4 $ b [3:0] $end
$var reg 1 % ci $end
$scope module dut $end
$var wire 4 & a [3:0] $end
$var wire 4 ' a_dlyd [3:0] $end
$var wire 4 ( b [3:0] $end
$var wire 4 ) b_dlyd [3:0] $end
$var wire 1 % ci $end
$var wire 1 * ci_dlyd $end
$var wire 1 " co $end
$var wire 4 + s [3:0] $end
$var wire 5 , sum [4:0] $end
$upscope $end
$scope begin $ivl_for_loop0 $end
$var integer 32 - i [31:0] $end
$scope begin $ivl_for_loop1 $end
$var integer 32 . j [31:0] $end
$upscope $end
$upscope $end
$upscope $end
$enddefinitions $end
$comment Show the parameter values. $end
$dumpall
$end
#0
$dumpvars
b0 .
b0 -
bx ,
bx +
x*
bx )
b0 (
bx '
b0 &
0%
b0 $
b0 #
x"
bx !
$end
#60
b0 ,
0*
b0 )
b0 '
#85
0"
#105
b0 !
b0 +
#200
1%
#260
b1 ,
1*
#305
b1 !
b1 +
#400
0%
b1 $
b1 (
b1 .
#460
0*
b1 ,
b1 )
#600
1%
#660
b10 ,
1*
#705
b10 !
b10 +
#800
0%
b10 $
b10 (
b10 .
#860
0*
b10 ,
b10 )
#1000
1%
#1060
b11 ,
1*
#1105
b11 !
b11 +
#1200
0%
b11 $
b11 (
b11 .
#1260
0*
b11 ,
b11 )
#1400
1%
#1460
b100 ,
1*
#1505
b100 !
b100 +
#1600
0%
b100 $
b100 (
b100 .
#1660
0*
b100 ,
b100 )
#1800
1%
#1860
b101 ,
1*
#1905
b101 !
b101 +
#2000
0%
b101 $
b101 (
b101 .
#2060
0*
b101 ,
b101 )
#2200
1%
#2260
b110 ,
1*
#2305
b110 !
b110 +
#2400
0%
b110 $
b110 (
b110 .
#2460
0*
b110 ,
b110 )
#2600
1%
#2660
b111 ,
1*
#2705
b111 !
b111 +
#2800
0%
b111 $
b111 (
b111 .
#2860
0*
b111 ,
b111 )
#3000
1%
#3060
b1000 ,
1*
#3105
b1000 !
b1000 +
#3200
0%
b1000 $
b1000 (
b1000 .
#3260
0*
b1000 ,
b1000 )
#3400
1%
#3460
b1001 ,
1*
#3505
b1001 !
b1001 +
#3600
0%
b1001 $
b1001 (
b1001 .
#3660
0*
b1001 ,
b1001 )
#3800
1%
#3860
b1010 ,
1*
#3905
b1010 !
b1010 +
#4000
0%
b1010 $
b1010 (
b1010 .
#4060
0*
b1010 ,
b1010 )
#4200
1%
#4260
b1011 ,
1*
#4305
b1011 !
b1011 +
#4400
0%
b1011 $
b1011 (
b1011 .
#4460
0*
b1011 ,
b1011 )
#4600
1%
#4660
b1100 ,
1*
#4705
b1100 !
b1100 +
#4800
0%
b1100 $
b1100 (
b1100 .
#4860
0*
b1100 ,
b1100 )
#5000
1%
#5060
b1101 ,
1*
#5105
b1101 !
b1101 +
#5200
0%
b1101 $
b1101 (
b1101 .
#5260
0*
b1101 ,
b1101 )
#5400
1%
#5460
b1110 ,
1*
#5505
b1110 !
b1110 +
#5600
0%
b1110 $
b1110 (
b1110 .
#5660
0*
b1110 ,
b1110 )
#5800
1%
#5860
b1111 ,
1*
#5905
b1111 !
b1111 +
#6000
0%
b1111 $
b1111 (
b1111 .
#6060
0*
b1111 ,
b1111 )
#6200
1%
#6260
b10000 ,
1*
#6285
1"
#6305
b0 !
b0 +
#6400
0%
b0 $
b0 (
b1 #
b1 &
b1 -
b0 .
#6460
0*
b0 )
b1 ,
b1 '
#6485
0"
#6505
b1 !
b1 +
#6600
1%
#6660
b10 ,
1*
#6705
b10 !
b10 +
#6800
0%
b1 $
b1 (
b1 .
#6860
0*
b10 ,
b1 )
#7000
1%
#7060
b11 ,
1*
#7105
b11 !
b11 +
#7200
0%
b10 $
b10 (
b10 .
#7260
0*
b11 ,
b10 )
#7400
1%
#7460
b100 ,
1*
#7505
b100 !
b100 +
#7600
0%
b11 $
b11 (
b11 .
#7660
0*
b100 ,
b11 )
#7800
1%
#7860
b101 ,
1*
#7905
b101 !
b101 +
#8000
0%
b100 $
b100 (
b100 .
#8060
0*
b101 ,
b100 )
#8200
1%
#8260
b110 ,
1*
#8305
b110 !
b110 +
#8400
0%
b101 $
b101 (
b101 .
#8460
0*
b110 ,
b101 )
#8600
1%
#8660
b111 ,
1*
#8705
b111 !
b111 +
#8800
0%
b110 $
b110 (
b110 .
#8860
0*
b111 ,
b110 )
#9000
1%
#9060
b1000 ,
1*
#9105
b1000 !
b1000 +
#9200
0%
b111 $
b111 (
b111 .
#9260
0*
b1000 ,
b111 )
#9400
1%
#9460
b1001 ,
1*
#9505
b1001 !
b1001 +
#9600
0%
b1000 $
b1000 (
b1000 .
#9660
0*
b1001 ,
b1000 )
#9800
1%
#9860
b1010 ,
1*
#9905
b1010 !
b1010 +
#10000
0%
b1001 $
b1001 (
b1001 .
#10060
0*
b1010 ,
b1001 )
#10200
1%
#10260
b1011 ,
1*
#10305
b1011 !
b1011 +
#10400
0%
b1010 $
b1010 (
b1010 .
#10460
0*
b1011 ,
b1010 )
#10600
1%
#10660
b1100 ,
1*
#10705
b1100 !
b1100 +
#10800
0%
b1011 $
b1011 (
b1011 .
#10860
0*
b1100 ,
b1011 )
#11000
1%
#11060
b1101 ,
1*
#11105
b1101 !
b1101 +
#11200
0%
b1100 $
b1100 (
b1100 .
#11260
0*
b1101 ,
b1100 )
#11400
1%
#11460
b1110 ,
1*
#11505
b1110 !
b1110 +
#11600
0%
b1101 $
b1101 (
b1101 .
#11660
0*
b1110 ,
b1101 )
#11800
1%
#11860
b1111 ,
1*
#11905
b1111 !
b1111 +
#12000
0%
b1110 $
b1110 (
b1110 .
#12060
0*
b1111 ,
b1110 )
#12200
1%
#12260
b10000 ,
1*
#12285
1"
#12305
b0 !
b0 +
#12400
0%
b1111 $
b1111 (
b1111 .
#12460
0*
b10000 ,
b1111 )
#12600
1%
#12660
b10001 ,
1*
#12705
b1 !
b1 +
#12800
0%
b0 $
b0 (
b10 #
b10 &
b10 -
b0 .
#12860
0*
b0 )
b10 ,
b10 '
#12885
0"
#12905
b10 !
b10 +
#13000
1%
#13060
b11 ,
1*
#13105
b11 !
b11 +
#13200
0%
b1 $
b1 (
b1 .
#13260
0*
b11 ,
b1 )
#13400
1%
#13460
b100 ,
1*
#13505
b100 !
b100 +
#13600
0%
b10 $
b10 (
b10 .
#13660
0*
b100 ,
b10 )
#13800
1%
#13860
b101 ,
1*
#13905
b101 !
b101 +
#14000
0%
b11 $
b11 (
b11 .
#14060
0*
b101 ,
b11 )
#14200
1%
#14260
b110 ,
1*
#14305
b110 !
b110 +
#14400
0%
b100 $
b100 (
b100 .
#14460
0*
b110 ,
b100 )
#14600
1%
#14660
b111 ,
1*
#14705
b111 !
b111 +
#14800
0%
b101 $
b101 (
b101 .
#14860
0*
b111 ,
b101 )
#15000
1%
#15060
b1000 ,
1*
#15105
b1000 !
b1000 +
#15200
0%
b110 $
b110 (
b110 .
#15260
0*
b1000 ,
b110 )
#15400
1%
#15460
b1001 ,
1*
#15505
b1001 !
b1001 +
#15600
0%
b111 $
b111 (
b111 .
#15660
0*
b1001 ,
b111 )
#15800
1%
#15860
b1010 ,
1*
#15905
b1010 !
b1010 +
#16000
0%
b1000 $
b1000 (
b1000 .
#16060
0*
b1010 ,
b1000 )
#16200
1%
#16260
b1011 ,
1*
#16305
b1011 !
b1011 +
#16400
0%
b1001 $
b1001 (
b1001 .
#16460
0*
b1011 ,
b1001 )
#16600
1%
#16660
b1100 ,
1*
#16705
b1100 !
b1100 +
#16800
0%
b1010 $
b1010 (
b1010 .
#16860
0*
b1100 ,
b1010 )
#17000
1%
#17060
b1101 ,
1*
#17105
b1101 !
b1101 +
#17200
0%
b1011 $
b1011 (
b1011 .
#17260
0*
b1101 ,
b1011 )
#17400
1%
#17460
b1110 ,
1*
#17505
b1110 !
b1110 +
#17600
0%
b1100 $
b1100 (
b1100 .
#17660
0*
b1110 ,
b1100 )
#17800
1%
#17860
b1111 ,
1*
#17905
b1111 !
b1111 +
#18000
0%
b1101 $
b1101 (
b1101 .
#18060
0*
b1111 ,
b1101 )
#18200
1%
#18260
b10000 ,
1*
#18285
1"
#18305
b0 !
b0 +
#18400
0%
b1110 $
b1110 (
b1110 .
#18460
0*
b10000 ,
b1110 )
#18600
1%
#18660
b10001 ,
1*
#18705
b1 !
b1 +
#18800
0%
b1111 $
b1111 (
b1111 .
#18860
0*
b10001 ,
b1111 )
#19000
1%
#19060
b10010 ,
1*
#19105
b10 !
b10 +
#19200
0%
b0 $
b0 (
b11 #
b11 &
b11 -
b0 .
#19260
0*
b0 )
b11 ,
b11 '
#19285
0"
#19305
b11 !
b11 +
#19400
1%
#19460
b100 ,
1*
#19505
b100 !
b100 +
#19600
0%
b1 $
b1 (
b1 .
#19660
0*
b100 ,
b1 )
#19800
1%
#19860
b101 ,
1*
#19905
b101 !
b101 +
#20000
0%
b10 $
b10 (
b10 .
#20060
0*
b101 ,
b10 )
#20200
1%
#20260
b110 ,
1*
#20305
b110 !
b110 +
#20400
0%
b11 $
b11 (
b11 .
#20460
0*
b110 ,
b11 )
#20600
1%
#20660
b111 ,
1*
#20705
b111 !
b111 +
#20800
0%
b100 $
b100 (
b100 .
#20860
0*
b111 ,
b100 )
#21000
1%
#21060
b1000 ,
1*
#21105
b1000 !
b1000 +
#21200
0%
b101 $
b101 (
b101 .
#21260
0*
b1000 ,
b101 )
#21400
1%
#21460
b1001 ,
1*
#21505
b1001 !
b1001 +
#21600
0%
b110 $
b110 (
b110 .
#21660
0*
b1001 ,
b110 )
#21800
1%
#21860
b1010 ,
1*
#21905
b1010 !
b1010 +
#22000
0%
b111 $
b111 (
b111 .
#22060
0*
b1010 ,
b111 )
#22200
1%
#22260
b1011 ,
1*
#22305
b1011 !
b1011 +
#22400
0%
b1000 $
b1000 (
b1000 .
#22460
0*
b1011 ,
b1000 )
#22600
1%
#22660
b1100 ,
1*
#22705
b1100 !
b1100 +
#22800
0%
b1001 $
b1001 (
b1001 .
#22860
0*
b1100 ,
b1001 )
#23000
1%
#23060
b1101 ,
1*
#23105
b1101 !
b1101 +
#23200
0%
b1010 $
b1010 (
b1010 .
#23260
0*
b1101 ,
b1010 )
#23400
1%
#23460
b1110 ,
1*
#23505
b1110 !
b1110 +
#23600
0%
b1011 $
b1011 (
b1011 .
#23660
0*
b1110 ,
b1011 )
#23800
1%
#23860
b1111 ,
1*
#23905
b1111 !
b1111 +
#24000
0%
b1100 $
b1100 (
b1100 .
#24060
0*
b1111 ,
b1100 )
#24200
1%
#24260
b10000 ,
1*
#24285
1"
#24305
b0 !
b0 +
#24400
0%
b1101 $
b1101 (
b1101 .
#24460
0*
b10000 ,
b1101 )
#24600
1%
#24660
b10001 ,
1*
#24705
b1 !
b1 +
#24800
0%
b1110 $
b1110 (
b1110 .
#24860
0*
b10001 ,
b1110 )
#25000
1%
#25060
b10010 ,
1*
#25105
b10 !
b10 +
#25200
0%
b1111 $
b1111 (
b1111 .
#25260
0*
b10010 ,
b1111 )
#25400
1%
#25460
b10011 ,
1*
#25505
b11 !
b11 +
#25600
0%
b0 $
b0 (
b100 #
b100 &
b100 -
b0 .
#25660
0*
b0 )
b100 ,
b100 '
#25685
0"
#25705
b100 !
b100 +
#25800
1%
#25860
b101 ,
1*
#25905
b101 !
b101 +
#26000
0%
b1 $
b1 (
b1 .
#26060
0*
b101 ,
b1 )
#26200
1%
#26260
b110 ,
1*
#26305
b110 !
b110 +
#26400
0%
b10 $
b10 (
b10 .
#26460
0*
b110 ,
b10 )
#26600
1%
#26660
b111 ,
1*
#26705
b111 !
b111 +
#26800
0%
b11 $
b11 (
b11 .
#26860
0*
b111 ,
b11 )
#27000
1%
#27060
b1000 ,
1*
#27105
b1000 !
b1000 +
#27200
0%
b100 $
b100 (
b100 .
#27260
0*
b1000 ,
b100 )
#27400
1%
#27460
b1001 ,
1*
#27505
b1001 !
b1001 +
#27600
0%
b101 $
b101 (
b101 .
#27660
0*
b1001 ,
b101 )
#27800
1%
#27860
b1010 ,
1*
#27905
b1010 !
b1010 +
#28000
0%
b110 $
b110 (
b110 .
#28060
0*
b1010 ,
b110 )
#28200
1%
#28260
b1011 ,
1*
#28305
b1011 !
b1011 +
#28400
0%
b111 $
b111 (
b111 .
#28460
0*
b1011 ,
b111 )
#28600
1%
#28660
b1100 ,
1*
#28705
b1100 !
b1100 +
#28800
0%
b1000 $
b1000 (
b1000 .
#28860
0*
b1100 ,
b1000 )
#29000
1%
#29060
b1101 ,
1*
#29105
b1101 !
b1101 +
#29200
0%
b1001 $
b1001 (
b1001 .
#29260
0*
b1101 ,
b1001 )
#29400
1%
#29460
b1110 ,
1*
#29505
b1110 !
b1110 +
#29600
0%
b1010 $
b1010 (
b1010 .
#29660
0*
b1110 ,
b1010 )
#29800
1%
#29860
b1111 ,
1*
#29905
b1111 !
b1111 +
#30000
0%
b1011 $
b1011 (
b1011 .
#30060
0*
b1111 ,
b1011 )
#30200
1%
#30260
b10000 ,
1*
#30285
1"
#30305
b0 !
b0 +
#30400
0%
b1100 $
b1100 (
b1100 .
#30460
0*
b10000 ,
b1100 )
#30600
1%
#30660
b10001 ,
1*
#30705
b1 !
b1 +
#30800
0%
b1101 $
b1101 (
b1101 .
#30860
0*
b10001 ,
b1101 )
#31000
1%
#31060
b10010 ,
1*
#31105
b10 !
b10 +
#31200
0%
b1110 $
b1110 (
b1110 .
#31260
0*
b10010 ,
b1110 )
#31400
1%
#31460
b10011 ,
1*
#31505
b11 !
b11 +
#31600
0%
b1111 $
b1111 (
b1111 .
#31660
0*
b10011 ,
b1111 )
#31800
1%
#31860
b10100 ,
1*
#31905
b100 !
b100 +
#32000
0%
b0 $
b0 (
b101 #
b101 &
b101 -
b0 .
#32060
0*
b0 )
b101 ,
b101 '
#32085
0"
#32105
b101 !
b101 +
#32200
1%
#32260
b110 ,
1*
#32305
b110 !
b110 +
#32400
0%
b1 $
b1 (
b1 .
#32460
0*
b110 ,
b1 )
#32600
1%
#32660
b111 ,
1*
#32705
b111 !
b111 +
#32800
0%
b10 $
b10 (
b10 .
#32860
0*
b111 ,
b10 )
#33000
1%
#33060
b1000 ,
1*
#33105
b1000 !
b1000 +
#33200
0%
b11 $
b11 (
b11 .
#33260
0*
b1000 ,
b11 )
#33400
1%
#33460
b1001 ,
1*
#33505
b1001 !
b1001 +
#33600
0%
b100 $
b100 (
b100 .
#33660
0*
b1001 ,
b100 )
#33800
1%
#33860
b1010 ,
1*
#33905
b1010 !
b1010 +
#34000
0%
b101 $
b101 (
b101 .
#34060
0*
b1010 ,
b101 )
#34200
1%
#34260
b1011 ,
1*
#34305
b1011 !
b1011 +
#34400
0%
b110 $
b110 (
b110 .
#34460
0*
b1011 ,
b110 )
#34600
1%
#34660
b1100 ,
1*
#34705
b1100 !
b1100 +
#34800
0%
b111 $
b111 (
b111 .
#34860
0*
b1100 ,
b111 )
#35000
1%
#35060
b1101 ,
1*
#35105
b1101 !
b1101 +
#35200
0%
b1000 $
b1000 (
b1000 .
#35260
0*
b1101 ,
b1000 )
#35400
1%
#35460
b1110 ,
1*
#35505
b1110 !
b1110 +
#35600
0%
b1001 $
b1001 (
b1001 .
#35660
0*
b1110 ,
b1001 )
#35800
1%
#35860
b1111 ,
1*
#35905
b1111 !
b1111 +
#36000
0%
b1010 $
b1010 (
b1010 .
#36060
0*
b1111 ,
b1010 )
#36200
1%
#36260
b10000 ,
1*
#36285
1"
#36305
b0 !
b0 +
#36400
0%
b1011 $
b1011 (
b1011 .
#36460
0*
b10000 ,
b1011 )
#36600
1%
#36660
b10001 ,
1*
#36705
b1 !
b1 +
#36800
0%
b1100 $
b1100 (
b1100 .
#36860
0*
b10001 ,
b1100 )
#37000
1%
#37060
b10010 ,
1*
#37105
b10 !
b10 +
#37200
0%
b1101 $
b1101 (
b1101 .
#37260
0*
b10010 ,
b1101 )
#37400
1%
#37460
b10011 ,
1*
#37505
b11 !
b11 +
#37600
0%
b1110 $
b1110 (
b1110 .
#37660
0*
b10011 ,
b1110 )
#37800
1%
#37860
b10100 ,
1*
#37905
b100 !
b100 +
#38000
0%
b1111 $
b1111 (
b1111 .
#38060
0*
b10100 ,
b1111 )
#38200
1%
#38260
b10101 ,
1*
#38305
b101 !
b101 +
#38400
0%
b0 $
b0 (
b110 #
b110 &
b110 -
b0 .
#38460
0*
b0 )
b110 ,
b110 '
#38485
0"
#38505
b110 !
b110 +
#38600
1%
#38660
b111 ,
1*
#38705
b111 !
b111 +
#38800
0%
b1 $
b1 (
b1 .
#38860
0*
b111 ,
b1 )
#39000
1%
#39060
b1000 ,
1*
#39105
b1000 !
b1000 +
#39200
0%
b10 $
b10 (
b10 .
#39260
0*
b1000 ,
b10 )
#39400
1%
#39460
b1001 ,
1*
#39505
b1001 !
b1001 +
#39600
0%
b11 $
b11 (
b11 .
#39660
0*
b1001 ,
b11 )
#39800
1%
#39860
b1010 ,
1*
#39905
b1010 !
b1010 +
#40000
0%
b100 $
b100 (
b100 .
#40060
0*
b1010 ,
b100 )
#40200
1%
#40260
b1011 ,
1*
#40305
b1011 !
b1011 +
#40400
0%
b101 $
b101 (
b101 .
#40460
0*
b1011 ,
b101 )
#40600
1%
#40660
b1100 ,
1*
#40705
b1100 !
b1100 +
#40800
0%
b110 $
b110 (
b110 .
#40860
0*
b1100 ,
b110 )
#41000
1%
#41060
b1101 ,
1*
#41105
b1101 !
b1101 +
#41200
0%
b111 $
b111 (
b111 .
#41260
0*
b1101 ,
b111 )
#41400
1%
#41460
b1110 ,
1*
#41505
b1110 !
b1110 +
#41600
0%
b1000 $
b1000 (
b1000 .
#41660
0*
b1110 ,
b1000 )
#41800
1%
#41860
b1111 ,
1*
#41905
b1111 !
b1111 +
#42000
0%
b1001 $
b1001 (
b1001 .
#42060
0*
b1111 ,
b1001 )
#42200
1%
#42260
b10000 ,
1*
#42285
1"
#42305
b0 !
b0 +
#42400
0%
b1010 $
b1010 (
b1010 .
#42460
0*
b10000 ,
b1010 )
#42600
1%
#42660
b10001 ,
1*
#42705
b1 !
b1 +
#42800
0%
b1011 $
b1011 (
b1011 .
#42860
0*
b10001 ,
b1011 )
#43000
1%
#43060
b10010 ,
1*
#43105
b10 !
b10 +
#43200
0%
b1100 $
b1100 (
b1100 .
#43260
0*
b10010 ,
b1100 )
#43400
1%
#43460
b10011 ,
1*
#43505
b11 !
b11 +
#43600
0%
b1101 $
b1101 (
b1101 .
#43660
0*
b10011 ,
b1101 )
#43800
1%
#43860
b10100 ,
1*
#43905
b100 !
b100 +
#44000
0%
b1110 $
b1110 (
b1110 .
#44060
0*
b10100 ,
b1110 )
#44200
1%
#44260
b10101 ,
1*
#44305
b101 !
b101 +
#44400
0%
b1111 $
b1111 (
b1111 .
#44460
0*
b10101 ,
b1111 )
#44600
1%
#44660
b10110 ,
1*
#44705
b110 !
b110 +
#44800
0%
b0 $
b0 (
b111 #
b111 &
b111 -
b0 .
#44860
0*
b0 )
b111 ,
b111 '
#44885
0"
#44905
b111 !
b111 +
#45000
1%
#45060
b1000 ,
1*
#45105
b1000 !
b1000 +
#45200
0%
b1 $
b1 (
b1 .
#45260
0*
b1000 ,
b1 )
#45400
1%
#45460
b1001 ,
1*
#45505
b1001 !
b1001 +
#45600
0%
b10 $
b10 (
b10 .
#45660
0*
b1001 ,
b10 )
#45800
1%
#45860
b1010 ,
1*
#45905
b1010 !
b1010 +
#46000
0%
b11 $
b11 (
b11 .
#46060
0*
b1010 ,
b11 )
#46200
1%
#46260
b1011 ,
1*
#46305
b1011 !
b1011 +
#46400
0%
b100 $
b100 (
b100 .
#46460
0*
b1011 ,
b100 )
#46600
1%
#46660
b1100 ,
1*
#46705
b1100 !
b1100 +
#46800
0%
b101 $
b101 (
b101 .
#46860
0*
b1100 ,
b101 )
#47000
1%
#47060
b1101 ,
1*
#47105
b1101 !
b1101 +
#47200
0%
b110 $
b110 (
b110 .
#47260
0*
b1101 ,
b110 )
#47400
1%
#47460
b1110 ,
1*
#47505
b1110 !
b1110 +
#47600
0%
b111 $
b111 (
b111 .
#47660
0*
b1110 ,
b111 )
#47800
1%
#47860
b1111 ,
1*
#47905
b1111 !
b1111 +
#48000
0%
b1000 $
b1000 (
b1000 .
#48060
0*
b1111 ,
b1000 )
#48200
1%
#48260
b10000 ,
1*
#48285
1"
#48305
b0 !
b0 +
#48400
0%
b1001 $
b1001 (
b1001 .
#48460
0*
b10000 ,
b1001 )
#48600
1%
#48660
b10001 ,
1*
#48705
b1 !
b1 +
#48800
0%
b1010 $
b1010 (
b1010 .
#48860
0*
b10001 ,
b1010 )
#49000
1%
#49060
b10010 ,
1*
#49105
b10 !
b10 +
#49200
0%
b1011 $
b1011 (
b1011 .
#49260
0*
b10010 ,
b1011 )
#49400
1%
#49460
b10011 ,
1*
#49505
b11 !
b11 +
#49600
0%
b1100 $
b1100 (
b1100 .
#49660
0*
b10011 ,
b1100 )
#49800
1%
#49860
b10100 ,
1*
#49905
b100 !
b100 +
#50000
0%
b1101 $
b1101 (
b1101 .
#50060
0*
b10100 ,
b1101 )
#50200
1%
#50260
b10101 ,
1*
#50305
b101 !
b101 +
#50400
0%
b1110 $
b1110 (
b1110 .
#50460
0*
b10101 ,
b1110 )
#50600
1%
#50660
b10110 ,
1*
#50705
b110 !
b110 +
#50800
0%
b1111 $
b1111 (
b1111 .
#50860
0*
b10110 ,
b1111 )
#51000
1%
#51060
b10111 ,
1*
#51105
b111 !
b111 +
#51200
0%
b0 $
b0 (
b1000 #
b1000 &
b1000 -
b0 .
#51260
0*
b0 )
b1000 ,
b1000 '
#51285
0"
#51305
b1000 !
b1000 +
#51400
1%
#51460
b1001 ,
1*
#51505
b1001 !
b1001 +
#51600
0%
b1 $
b1 (
b1 .
#51660
0*
b1001 ,
b1 )
#51800
1%
#51860
b1010 ,
1*
#51905
b1010 !
b1010 +
#52000
0%
b10 $
b10 (
b10 .
#52060
0*
b1010 ,
b10 )
#52200
1%
#52260
b1011 ,
1*
#52305
b1011 !
b1011 +
#52400
0%
b11 $
b11 (
b11 .
#52460
0*
b1011 ,
b11 )
#52600
1%
#52660
b1100 ,
1*
#52705
b1100 !
b1100 +
#52800
0%
b100 $
b100 (
b100 .
#52860
0*
b1100 ,
b100 )
#53000
1%
#53060
b1101 ,
1*
#53105
b1101 !
b1101 +
#53200
0%
b101 $
b101 (
b101 .
#53260
0*
b1101 ,
b101 )
#53400
1%
#53460
b1110 ,
1*
#53505
b1110 !
b1110 +
#53600
0%
b110 $
b110 (
b110 .
#53660
0*
b1110 ,
b110 )
#53800
1%
#53860
b1111 ,
1*
#53905
b1111 !
b1111 +
#54000
0%
b111 $
b111 (
b111 .
#54060
0*
b1111 ,
b111 )
#54200
1%
#54260
b10000 ,
1*
#54285
1"
#54305
b0 !
b0 +
#54400
0%
b1000 $
b1000 (
b1000 .
#54460
0*
b10000 ,
b1000 )
#54600
1%
#54660
b10001 ,
1*
#54705
b1 !
b1 +
#54800
0%
b1001 $
b1001 (
b1001 .
#54860
0*
b10001 ,
b1001 )
#55000
1%
#55060
b10010 ,
1*
#55105
b10 !
b10 +
#55200
0%
b1010 $
b1010 (
b1010 .
#55260
0*
b10010 ,
b1010 )
#55400
1%
#55460
b10011 ,
1*
#55505
b11 !
b11 +
#55600
0%
b1011 $
b1011 (
b1011 .
#55660
0*
b10011 ,
b1011 )
#55800
1%
#55860
b10100 ,
1*
#55905
b100 !
b100 +
#56000
0%
b1100 $
b1100 (
b1100 .
#56060
0*
b10100 ,
b1100 )
#56200
1%
#56260
b10101 ,
1*
#56305
b101 !
b101 +
#56400
0%
b1101 $
b1101 (
b1101 .
#56460
0*
b10101 ,
b1101 )
#56600
1%
#56660
b10110 ,
1*
#56705
b110 !
b110 +
#56800
0%
b1110 $
b1110 (
b1110 .
#56860
0*
b10110 ,
b1110 )
#57000
1%
#57060
b10111 ,
1*
#57105
b111 !
b111 +
#57200
0%
b1111 $
b1111 (
b1111 .
#57260
0*
b10111 ,
b1111 )
#57400
1%
#57460
b11000 ,
1*
#57505
b1000 !
b1000 +
#57600
0%
b0 $
b0 (
b1001 #
b1001 &
b1001 -
b0 .
#57660
0*
b0 )
b1001 ,
b1001 '
#57685
0"
#57705
b1001 !
b1001 +
#57800
1%
#57860
b1010 ,
1*
#57905
b1010 !
b1010 +
#58000
0%
b1 $
b1 (
b1 .
#58060
0*
b1010 ,
b1 )
#58200
1%
#58260
b1011 ,
1*
#58305
b1011 !
b1011 +
#58400
0%
b10 $
b10 (
b10 .
#58460
0*
b1011 ,
b10 )
#58600
1%
#58660
b1100 ,
1*
#58705
b1100 !
b1100 +
#58800
0%
b11 $
b11 (
b11 .
#58860
0*
b1100 ,
b11 )
#59000
1%
#59060
b1101 ,
1*
#59105
b1101 !
b1101 +
#59200
0%
b100 $
b100 (
b100 .
#59260
0*
b1101 ,
b100 )
#59400
1%
#59460
b1110 ,
1*
