src/verilog/F74F283.sv

module F74F283(
    input logic  [3:0] a,
    input logic  [3:0] b,
    input logic        ci,
    output logic [3:0] s,
    output logic       co
);
    logic [4:0] sum;
    logic [3:0] a_dlyd, b_dlyd;

    /* Delays are added to inputs and output to match datasheet values as 
       close as possible. When Tphl and Tplh differ, the worst is taken.
       This is done because a transition at one input may cause an output
       to go high or low. A more detailed model would be needed to capture
       that behavior correctly. */
    buf #(2:4:6) I0( ci_dlyd, ci);
    buf #(2:4:6) I1[3:0]( a_dlyd, a);
    buf #(2:4:6) I2[3:0]( b_dlyd, b);

    assign sum = {1'b0,a_dlyd} + {1'b0,b_dlyd} + ci_dlyd;

    buf #(4:3:4.5) I3[3:0]( s, sum[3:0]);
    buf #(1.5:1.7:2.5) I4( co, sum[4]);
endmodule



module ttl_74F377(
    input  logic       clk,
    input  logic       nEN,
    input  logic [7:0] D,
    output logic [7:0] Q
);
logic Qi;

always_ff @(posedge clk) begin
    if (clk && nEN == 1'b0)
        Qi <= D;
end

assign #(3.0:6.0:7.5,4.0:7.0:9.0) Q = Qi;

    specify
        // $setuphold(reference, data, setup_time, hold_time)
        $setuphold(posedge clk, D, 3.5, 1.0); 
        $setuphold(posedge clk, nEN, 4.1, 2.0); 
    endspecify
endmodule



module ttl_74F244(
    output logic [3:0] Y,
    input  logic [3:0] D,
    input  logic       nOE
);
    logic       nOE1i, nOE2i;
    logic [3:0] Di, nDi;
    wire  [3:0] y;

    buf #( 1.0:1.0:1.2, 1.0:1.0:1.5) I1a(  Di[0], D[0]);
    buf #( 1.0:1.0:1.2, 1.0:1.0:1.5) I1b(  Di[1], D[1]);
    buf #( 1.0:1.0:1.2, 1.0:1.0:1.5) I1c(  Di[2], D[2]);
    buf #( 1.0:1.0:1.2, 1.0:1.0:1.5) I1d(  Di[3], D[3]);

    not #( 1.0:1.0:1.5, 1.0:1.0:1.2) I2a( nDi[0], D[0]);
    not #( 1.0:1.0:1.5, 1.0:1.0:1.2) I2b( nDi[1], D[1]);
    not #( 1.0:1.0:1.5, 1.0:1.0:1.2) I2c( nDi[2], D[2]);
    not #( 1.0:1.0:1.5, 1.0:1.0:1.2) I2d( nDi[3], D[3]);

    buf #( 0.5:1.5:2.0, 0.5:1.3:1.7) I3( nOEh, nOE);
    buf #( 0.5:1.5:2.0, 0.5:2.4:3.0) I4( nOEl, nOE);

    bufif0 #( 1.5:3.0:5.0, 1.5:3.0:5.0, 1.5:3.0:5.0) I4ha( y[0], 4'b1111, nOEh |  nDi[0]);
    bufif0 #( 1.5:3.0:5.0, 1.5:3.0:5.0, 1.5:3.0:5.0) I4la( y[0], 4'b0000, nOEl |   Di[0]);
    bufif0 #( 1.5:3.0:5.0, 1.5:3.0:5.0, 1.5:3.0:5.0) I4hb( y[1], 4'b1111, nOEh |  nDi[1]);
    bufif0 #( 1.5:3.0:5.0, 1.5:3.0:5.0, 1.5:3.0:5.0) I4lb( y[1], 4'b0000, nOEl |   Di[1]);
    bufif0 #( 1.5:3.0:5.0, 1.5:3.0:5.0, 1.5:3.0:5.0) I4hc( y[2], 4'b1111, nOEh |  nDi[2]);
    bufif0 #( 1.5:3.0:5.0, 1.5:3.0:5.0, 1.5:3.0:5.0) I4lc( y[2], 4'b0000, nOEl |   Di[2]);
    bufif0 #( 1.5:3.0:5.0, 1.5:3.0:5.0, 1.5:3.0:5.0) I4hd( y[3], 4'b1111, nOEh |  nDi[3]);
    bufif0 #( 1.5:3.0:5.0, 1.5:3.0:5.0, 1.5:3.0:5.0) I4ld( y[3], 4'b0000, nOEl |   Di[3]);
    assign Y = y;
endmodule

/*********
  To do:
    Priority:
      74F244, 74F245, 74F374/574, 74F182, 74F381, 74F382, 74F157
      74F138, 4-bit sync counter with load and reset, 74F74, 74F174/6
      SRAM: 8kx8, 32kx8, 64kx8
    Maybe:
      74F181
*********/

src/verilog/ttl_74F244_tb.sv

`timescale 1ns / 100ps
`include "F74F283.sv"

module tb;
    logic [3:0] d, y;
    logic nOE;

    ttl_74F244 dut( y, d, nOE);

    initial begin
        $display("\n", `__FILE__, " - Starting simulation.");
        $dumpfile("./vcd/ttl_74F244_tb.vcd");
        $dumpvars(0, tb);

        d  = 4'b1010;
        nOE = 1'b0;

        #20 nOE = 1'b1;
        #20 nOE = 1'b0;
        #20 d   = 4'b0101; 

        #20;
        $display( `__FILE__, " - Test complete!\n");
        $finish;
    end

    initial begin
        $monitor("Time=%0t, d=%b, nOE=%b, y=%b", $time, d, nOE, y);
    end
endmodule

src/verilog/vcd/ttl_74F244_tb.vcd
$date
	Sun Feb 22 17:11:11 2026
$end
$version
	Icarus Verilog
$end
$timescale
	100ps
$end
$scope module tb $end
$var wire 4 ! y [3:0] $end
$var reg 4 " d [3:0] $end
$var reg 1 # nOE $end
$scope module dut $end
$var wire 4 $ D [3:0] $end
$var wire 4 % Y [3:0] $end
$var wire 1 # nOE $end
$var wire 1 & nOEh $end
$var wire 1 ' nOEl $end
$var wire 4 ( y [3:0] $end
$var wire 4 ) nDi [3:0] $end
$var wire 4 * Di [3:0] $end
$upscope $end
$upscope $end
$enddefinitions $end
$comment Show the parameter values. $end
$dumpall
$end
#0
$dumpvars
bx *
bx )
bx (
x'
x&
bx %
b1010 $
0#
b1010 "
bx !
$end
#10
b1010 *
b101 )
#13
0&
#24
0'
#40
bx (
#43
b1x1x !
b1x1x %
b1x1x (
#54
b1010 !
b1010 %
b1010 (
#200
1#
#215
1&
1'
#245
bz !
bz %
bz (
#400
0#
#413
0&
#424
0'
#443
b1z1z !
b1z1z %
b1z1z (
#454
b1010 !
b1010 %
b1010 (
#600
b101 "
b101 $
#610
b101 *
b1010 )
#640
b101 !
b101 %
b101 (
